ts_pip_scan/__init__.py
ts_pip_scan/commands.py
ts_pip_scan/models.py
ts_pip_scan/scanner.py
ts_pip_scan/ts_client.py
ts_pip_scan-1.0.3.dist-info/LICENSE
ts_pip_scan-1.0.3.dist-info/METADATA
ts_pip_scan-1.0.3.dist-info/WHEEL
ts_pip_scan-1.0.3.dist-info/entry_points.txt
ts_pip_scan-1.0.3.dist-info/top_level.txt
ts_pip_scan-1.0.3.dist-info/RECORD
