Metadata-Version: 2.1
Name: ts-pip-scan
Version: 1.0.3
Summary: TrustSource plugin for scanning python project installed pip dependencies and uploading them to [TrustSource](https://app.trustsource.io) via its API for code compliance evaluation
Author: Joseph Manyiel
Maintainer-email: Joseph Manyiel <jmagany@gmail.com>
License: Apache 2.0
Project-URL: Homepage, https://github.com/JoeMabor/TrustSource-pip-scan
Project-URL: Repository, https://github.com/JoeMabor/TrustSource-pip-scan.git
Classifier: License :: OSI Approved :: Apache Software License
Classifier: Programming Language :: Python :: 3
Classifier: Programming Language :: Python :: 3.9
Classifier: Programming Language :: Python :: 3.10
Classifier: Programming Language :: Python :: 3.12
Requires-Python: >=3.9
License-File: LICENSE
Requires-Dist: click >=8.1.7
Requires-Dist: httpx
Requires-Dist: GitPython
Requires-Dist: pydantic
